polars_quant-0.4.0.dist-info/METADATA
polars_quant-0.4.0.dist-info/WHEEL
polars_quant-0.4.0.dist-info/licenses/LICENSE
polars_quant/__init__.py
polars_quant/polars_quant.pyd
polars_quant/polars_quant.pyi
polars_quant-0.4.0.dist-info/RECORD
