Metadata-Version: 2.4
Name: polars-quant
Version: 0.4.0
Requires-Dist: polars>=1.33.1
Requires-Dist: pyarrow>=21.0.0
License-File: LICENSE
Summary: Blazingly Fast Polars Quant Tool
Author-email: Firstastor <23150126@hdu.edu.cn>
Requires-Python: >=3.9
